magnet/__init__.py
magnet/_version.py
magnet/constants.py
magnet/core.py
magnet/io.py
magnet/magnet.ini
magnet/net.py
magnet/plots.py
magnet/data/3C90_database.h5
magnet/data/3C90_datasheet.h5
magnet/data/3C90_datasheet_interpolated.h5
magnet/data/3C90_sinusoidal_interpolated.h5
magnet/data/3C94_database.h5
magnet/data/3C94_datasheet.h5
magnet/data/3C94_datasheet_interpolated.h5
magnet/data/3C94_sinusoidal_interpolated.h5
magnet/data/3E6_database.h5
magnet/data/3E6_datasheet.h5
magnet/data/3E6_datasheet_interpolated.h5
magnet/data/3E6_sinusoidal_interpolated.h5
magnet/data/3F4_database.h5
magnet/data/3F4_datasheet.h5
magnet/data/3F4_datasheet_interpolated.h5
magnet/data/3F4_sinusoidal_interpolated.h5
magnet/data/77_database.h5
magnet/data/77_datasheet.h5
magnet/data/77_datasheet_interpolated.h5
magnet/data/77_sinusoidal_interpolated.h5
magnet/data/78_database.h5
magnet/data/78_datasheet.h5
magnet/data/78_datasheet_interpolated.h5
magnet/data/78_sinusoidal_interpolated.h5
magnet/data/N27_database.h5
magnet/data/N27_datasheet.h5
magnet/data/N27_datasheet_interpolated.h5
magnet/data/N27_sinusoidal_interpolated.h5
magnet/data/N30_database.h5
magnet/data/N30_datasheet.h5
magnet/data/N30_datasheet_interpolated.h5
magnet/data/N30_sinusoidal_interpolated.h5
magnet/data/N49_database.h5
magnet/data/N49_datasheet.h5
magnet/data/N49_datasheet_interpolated.h5
magnet/data/N49_sinusoidal_interpolated.h5
magnet/data/N87_database.h5
magnet/data/N87_datasheet.h5
magnet/data/N87_datasheet_interpolated.h5
magnet/data/N87_sinusoidal_interpolated.h5
magnet/data/__init__.py
magnet/models/Model_3C90_LSTM.sd
magnet/models/Model_3C90_Sinusoidal.sd
magnet/models/Model_3C90_Trapezoidal.sd
magnet/models/Model_3C94_LSTM.sd
magnet/models/Model_3C94_Sinusoidal.sd
magnet/models/Model_3C94_Trapezoidal.sd
magnet/models/Model_3E6_LSTM.sd
magnet/models/Model_3E6_Sinusoidal.sd
magnet/models/Model_3E6_Trapezoidal.sd
magnet/models/Model_3F4_LSTM.sd
magnet/models/Model_3F4_Sinusoidal.sd
mag_net-0.1.0.dist-info/LICENSE
mag_net-0.1.0.dist-info/METADATA
mag_net-0.1.0.dist-info/WHEEL
mag_net-0.1.0.dist-info/top_level.txt
mag_net-0.1.0.dist-info/RECORD
