Metadata-Version: 2.1
Name: mag-net
Version: 0.1.0
Summary: Magnetic Core Loss Modeling using ML
License: UNKNOWN
Platform: UNKNOWN
Requires-Python: >=3.7
License-File: LICENSE
Requires-Dist: numpy
Requires-Dist: pandas
Requires-Dist: scipy
Requires-Dist: torch
Provides-Extra: dev
Requires-Dist: pytest ; extra == 'dev'
Requires-Dist: sphinx ; extra == 'dev'
Requires-Dist: numpydoc ; extra == 'dev'
Requires-Dist: sphinxcontrib-bibtex (<2.0.0) ; extra == 'dev'
Requires-Dist: sphinx-rtd-theme ; extra == 'dev'
